djangocms_twitter/models.py
djangocms_twitter/__init__.py
djangocms_twitter/cms_plugins.py
djangocms_twitter/south_migrations/__init__.py
djangocms_twitter/south_migrations/0001_initial.py
djangocms_twitter/south_migrations/0002_auto__add_twittersearch.py
djangocms_twitter/south_migrations/0004_rename_tables.py
djangocms_twitter/south_migrations/0003_auto__add_field_twitterrecententries_twitter_id__add_field_twittersear.py
djangocms_twitter/templates/cms/plugins/twitter_timeline.html
djangocms_twitter/templates/cms/plugins/twitter_search_widget.html
djangocms_twitter/migrations/__init__.py
djangocms_twitter/migrations/0001_initial.py
djangocms_twitter-0.0.5.dist-info/metadata.json
djangocms_twitter-0.0.5.dist-info/RECORD
djangocms_twitter-0.0.5.dist-info/METADATA
djangocms_twitter-0.0.5.dist-info/DESCRIPTION.rst
djangocms_twitter-0.0.5.dist-info/top_level.txt
djangocms_twitter-0.0.5.dist-info/WHEEL
djangocms_twitter-0.0.5.dist-info/LICENSE.txt
