Metadata-Version: 2.0
Name: djangocms-twitter
Version: 0.0.5
Summary: Twitter plugin for django CMS
Home-page: https://github.com/nephila/djangocms_twitter
Author: Nephila s.a.s.
Author-email: web@nephila.it
License: LICENSE.txt
Platform: OS Independent
Classifier: Development Status :: 4 - Beta
Classifier: Environment :: Web Environment
Classifier: Framework :: Django
Classifier: Intended Audience :: Developers
Classifier: License :: OSI Approved :: BSD License
Classifier: Operating System :: OS Independent
Classifier: Programming Language :: Python
Classifier: Topic :: Communications
Classifier: Topic :: Internet :: WWW/HTTP :: Dynamic Content
Classifier: Topic :: Internet :: WWW/HTTP :: Dynamic Content :: Message Boards
Classifier: Programming Language :: Python :: 2.6
Classifier: Programming Language :: Python :: 2.7
Requires-Dist: django-cms (>=3.0)
